{"allowModDistribution":true,"screenshots":[],"classId":6,"latestFilesIndexes":[{"filename":"mcjtylib-1.21-9.0.5.jar","releaseType":2,"gameVersion":"1.21.1","gameVersionTypeId":77784,"modLoader":6,"fileId":5961438},{"filename":"mcjtylib-1.21-9.0.3.jar","releaseType":2,"gameVersion":"1.21.1","gameVersionTypeId":77784,"modLoader":null,"fileId":5830986},{"filename":"mcjtylib-1.20-8.0.6.jar","releaseType":1,"gameVersion":"1.20.1","gameVersionTypeId":75125,"modLoader":1,"fileId":5613231},{"filename":"mcjtylib-1.19-7.2.8.jar","releaseType":1,"gameVersion":"1.19.2","gameVersionTypeId":73407,"modLoader":1,"fileId":5613229},{"filename":"mcjtylib-1.20-8.0.2.jar","releaseType":2,"gameVersion":"1.20.1","gameVersionTypeId":75125,"modLoader":1,"fileId":4691718},{"filename":"mcjtylib-1.19.4-7.2.7.jar","releaseType":1,"gameVersion":"1.19.4","gameVersionTypeId":73407,"modLoader":1,"fileId":4656167},{"filename":"mcjtylib-1.19.3-7.2.5.jar","releaseType":1,"gameVersion":"1.19.3","gameVersionTypeId":73407,"modLoader":1,"fileId":4501792},{"filename":"mcjtylib-1.18-6.0.20.jar","releaseType":1,"gameVersion":"1.18.2","gameVersionTypeId":73250,"modLoader":1,"fileId":4277564},{"filename":"mcjtylib-1.19-7.0.2.jar","releaseType":2,"gameVersion":"1.19.2","gameVersionTypeId":73407,"modLoader":1,"fileId":3920706},{"filename":"mcjtylib-1.19-7.0.1.jar","releaseType":2,"gameVersion":"1.19.1","gameVersionTypeId":73407,"modLoader":1,"fileId":3906996},{"filename":"mcjtylib-1.19-7.0.1.jar","releaseType":2,"gameVersion":"1.19","gameVersionTypeId":73407,"modLoader":1,"fileId":3906996},{"filename":"mcjtylib-1.16-5.1.8.jar","releaseType":1,"gameVersion":"1.16.5","gameVersionTypeId":70886,"modLoader":1,"fileId":3848282},{"filename":"mcjtylib-1.18-6.0.13.jar","releaseType":2,"gameVersion":"1.18.2","gameVersionTypeId":73250,"modLoader":1,"fileId":3757792},{"filename":"mcjtylib-1.18-6.0.10.jar","releaseType":2,"gameVersion":"1.18.1","gameVersionTypeId":73250,"modLoader":1,"fileId":3665826},{"filename":"mcjtylib-1.16-5.0.16.jar","releaseType":1,"gameVersion":"1.16.3","gameVersionTypeId":70886,"modLoader":1,"fileId":3194349},{"filename":"mcjtylib-1.16-5.0.16.jar","releaseType":1,"gameVersion":"1.16.4","gameVersionTypeId":70886,"modLoader":1,"fileId":3194349},{"filename":"mcjtylib-1.15-4.1.13.jar","releaseType":1,"gameVersion":"1.15.2","gameVersionTypeId":68722,"modLoader":1,"fileId":3131240},{"filename":"mcjtylib-1.16-5.0.8.jar","releaseType":1,"gameVersion":"1.16.2","gameVersionTypeId":70886,"modLoader":1,"fileId":3060309},{"filename":"mcjtylib-1.16-5.0.6.jar","releaseType":2,"gameVersion":"1.16.2","gameVersionTypeId":70886,"modLoader":1,"fileId":3051747},{"filename":"mcjtylib-1.15-4.1.3-beta.jar","releaseType":2,"gameVersion":"1.15.2","gameVersionTypeId":68722,"modLoader":1,"fileId":3014094},{"filename":"mcjtylib-1.14-3.5.17-alpha.jar","releaseType":2,"gameVersion":"1.14.4","gameVersionTypeId":64806,"modLoader":1,"fileId":2843740},{"filename":"mcjtylib-1.14-3.5.6-alpha.jar","releaseType":3,"gameVersion":"1.14.4","gameVersionTypeId":64806,"modLoader":null,"fileId":2758508},{"filename":"mcjtylib-1.12-3.5.4.jar","releaseType":1,"gameVersion":"1.12.2","gameVersionTypeId":628,"modLoader":null,"fileId":2745846},{"filename":"mcjtylib-1.14-3.5.4-alpha.jar","releaseType":3,"gameVersion":"1.14.3","gameVersionTypeId":64806,"modLoader":null,"fileId":2734698},{"filename":"mcjtylib-1.14-3.5.3-alpha.jar","releaseType":3,"gameVersion":"1.14.2","gameVersionTypeId":64806,"modLoader":null,"fileId":2725275},{"filename":"mcjtylib-1.12-3.0.0-alpha.jar","releaseType":3,"gameVersion":"1.12.2","gameVersionTypeId":628,"modLoader":null,"fileId":2567259},{"filename":"mcjtylib-1.1x-2.5.3.jar","releaseType":1,"gameVersion":"1.10.2","gameVersionTypeId":572,"modLoader":null,"fileId":2532014},{"filename":"mcjtylib-1.1x-2.5.3.jar","releaseType":1,"gameVersion":"1.11.2","gameVersionTypeId":599,"modLoader":null,"fileId":2532014},{"filename":"mcjtylib-1.12-2.5.0.jar","releaseType":1,"gameVersion":"1.12.1","gameVersionTypeId":628,"modLoader":null,"fileId":2501450},{"filename":"mcjtylib-1.12-2.4.4.jar","releaseType":1,"gameVersion":"1.12","gameVersionTypeId":628,"modLoader":null,"fileId":2451959},{"filename":"mcjtylib-1.12-2.4.3.jar","releaseType":2,"gameVersion":"1.12","gameVersionTypeId":628,"modLoader":null,"fileId":2445321},{"filename":"mcjtylib-1.1x-2.3.8.jar","releaseType":1,"gameVersion":"1.11","gameVersionTypeId":599,"modLoader":null,"fileId":2382741},{"filename":"mcjtylib-1.11-2.2.0beta1.jar","releaseType":2,"gameVersion":"1.10.2","gameVersionTypeId":572,"modLoader":null,"fileId":2351204},{"filename":"mcjtylib-1.11-2.2.0beta1.jar","releaseType":2,"gameVersion":"1.11","gameVersionTypeId":599,"modLoader":null,"fileId":2351204},{"filename":"mcjtylib-1.11-2.2.0alpha11.jar","releaseType":3,"gameVersion":"1.10.2","gameVersionTypeId":572,"modLoader":null,"fileId":2350547},{"filename":"mcjtylib-1.11-2.2.0alpha11.jar","releaseType":3,"gameVersion":"1.11","gameVersionTypeId":599,"modLoader":null,"fileId":2350547},{"filename":"mcjtylib-1.10-1.9.9.jar","releaseType":1,"gameVersion":"1.9.4","gameVersionTypeId":552,"modLoader":null,"fileId":2319056},{"filename":"mcjtylib-1.10-1.9.9.jar","releaseType":1,"gameVersion":"1.10","gameVersionTypeId":572,"modLoader":null,"fileId":2319056},{"filename":"mcjtylib-1.9.0-1.8.6.jar","releaseType":1,"gameVersion":"1.9","gameVersionTypeId":552,"modLoader":null,"fileId":2301101},{"filename":"mcjtylib-1.9.0-1.8.1beta15.jar","releaseType":2,"gameVersion":"1.9","gameVersionTypeId":552,"modLoader":null,"fileId":2293655},{"filename":"mcjtylib-1.8.9-1.8.1beta10.jar","releaseType":2,"gameVersion":"1.8.9","gameVersionTypeId":4,"modLoader":null,"fileId":2289589},{"filename":"mcjtylib-1.8.1.jar","releaseType":1,"gameVersion":"1.7.10","gameVersionTypeId":5,"modLoader":null,"fileId":2272449},{"filename":"mcjtylib188-1.8.0beta1.jar","releaseType":2,"gameVersion":"1.8.8","gameVersionTypeId":4,"modLoader":null,"fileId":2272085},{"filename":"mcjtylib-1.00beta1.jar","releaseType":2,"gameVersion":"1.7.10","gameVersionTypeId":5,"modLoader":null,"fileId":2248758}],"dateCreated":"2015-07-24T11:56:27.99Z","logo":{"description":"","id":21825,"title":"635733177880067480.png","modId":233105,"url":"https://media.forgecdn.net/avatars/21/825/635733177880067480.png","thumbnailUrl":"https://media.forgecdn.net/avatars/thumbnails/21/825/256/256/635733177880067480.png"},"links":{"sourceUrl":null,"issuesUrl":"https://github.com/McJty/McJtyLib/issues","websiteUrl":"https://www.curseforge.com/minecraft/mc-mods/mcjtylib","wikiUrl":""},"dateReleased":"2024-12-04T05:50:51.633Z","id":233105,"categories":[{"gameId":432,"classId":6,"name":"API and Library","dateModified":"2014-05-23T03:21:44.06Z","parentCategoryId":6,"id":421,"iconUrl":"https://media.forgecdn.net/avatars/6/36/635351496947765531.png","slug":"library-api","url":"https://www.curseforge.com/minecraft/mc-mods/library-api","displayIndex":0,"class":false}],"slug":"mcjtylib","gameId":432,"summary":"Companion mod for all mods by McJty (RFTools, XNet, Deep Resonance, Not Enough Wands, SignTastic, ...))","latestFiles":[{"gameId":432,"fileName":"mcjtylib-1.12-3.5.4.jar","gameVersions":["1.12.2"],"displayName":"McJtyLib - 1.12-3.5.4","sortableGameVersions":[{"gameVersionPadded":"0000000001.0000000012.0000000002","gameVersion":"1.12.2","gameVersionReleaseDate":"2017-09-18T05:00:00Z","gameVersionName":"1.12.2","gameVersionTypeId":628}],"downloadUrl":"https://edge.forgecdn.net/files/2745/846/mcjtylib-1.12-3.5.4.jar","fileDate":"2019-07-22T03:27:04.243Z","exposeAsAlternative":null,"modId":233105,"modules":[{"name":"META-INF","fingerprint":3642991143},{"name":"mcjty","fingerprint":1987490093},{"name":"mcmod.info","fingerprint":2959765002},{"name":"assets","fingerprint":847320386}],"dependencies":[{"relationType":2,"modId":245211},{"relationType":2,"modId":270789}],"fileFingerprint":285741512,"fileStatus":4,"releaseType":1,"hashes":[{"value":"8f3e381c4aea651f55ed1cd35fd69613fcd7f9da","algo":1},{"value":"45ac9983da9fd2bc7fe3446b9f4287c1","algo":2}],"parentProjectFileId":null,"alternateFileId":0,"id":2745846,"fileLength":544856,"downloadCount":35691714,"serverPackFileId":null,"serverPack":false,"available":false},{"gameId":432,"fileName":"mcjtylib-1.14-3.5.6-alpha.jar","gameVersions":["1.14.4"],"displayName":"mcjtylib-1.14-3.5.6-alpha.jar","sortableGameVersions":[{"gameVersionPadded":"0000000001.0000000014.0000000004","gameVersion":"1.14.4","gameVersionReleaseDate":"2019-07-19T00:00:00Z","gameVersionName":"1.14.4","gameVersionTypeId":64806}],"downloadUrl":"https://edge.forgecdn.net/files/2758/508/mcjtylib-1.14-3.5.6-alpha.jar","fileDate":"2019-08-10T04:29:59.073Z","exposeAsAlternative":null,"modId":233105,"modules":[{"name":"META-INF","fingerprint":662525897},{"name":"mcjty","fingerprint":1942901048},{"name":"assets","fingerprint":847320386},{"name":"pack.mcmeta","fingerprint":3650016781}],"dependencies":[{"relationType":2,"modId":245211},{"relationType":2,"modId":270789}],"fileFingerprint":1174377009,"fileStatus":4,"releaseType":3,"hashes":[{"value":"fc210077fd0c927b119742b9f9f2e7f3e63e0e4a","algo":1},{"value":"b01ca4d975d8bbf0da8b1fd411251ffc","algo":2}],"parentProjectFileId":null,"alternateFileId":0,"id":2758508,"fileLength":478687,"downloadCount":80147,"serverPackFileId":null,"serverPack":false,"available":false},{"gameId":432,"fileName":"mcjtylib-1.20-8.0.2.jar","gameVersions":["1.20.1","Forge"],"displayName":"McJtyLib - 1.20-8.0.2","sortableGameVersions":[{"gameVersionPadded":"0000000001.0000000020.0000000001","gameVersion":"1.20.1","gameVersionReleaseDate":"2023-06-12T14:26:38.477Z","gameVersionName":"1.20.1","gameVersionTypeId":75125},{"gameVersionPadded":"0","gameVersion":"","gameVersionReleaseDate":"2022-10-01T00:00:00Z","gameVersionName":"Forge","gameVersionTypeId":68441}],"downloadUrl":"https://edge.forgecdn.net/files/4691/718/mcjtylib-1.20-8.0.2.jar","fileDate":"2023-08-10T05:01:32.977Z","exposeAsAlternative":null,"modId":233105,"modules":[{"name":"META-INF","fingerprint":2993427905},{"name":"mcjty","fingerprint":1061473814},{"name":"assets","fingerprint":3529305187},{"name":"pack.mcmeta","fingerprint":3310931799}],"dependencies":[{"relationType":2,"modId":245211}],"fileFingerprint":277431986,"fileStatus":4,"releaseType":2,"hashes":[{"value":"5fbbd9908754a3816bce2e857c1050f9fa0e7339","algo":1},{"value":"eec874daf6f8a3ddb140fb72eaf48f23","algo":2}],"parentProjectFileId":null,"alternateFileId":0,"id":4691718,"fileLength":677584,"downloadCount":249288,"serverPackFileId":null,"serverPack":false,"available":false},{"gameId":432,"fileName":"mcjtylib-1.20-8.0.6.jar","gameVersions":["1.20.1","Forge"],"displayName":"McJtyLib - 1.20-8.0.6","sortableGameVersions":[{"gameVersionPadded":"0000000001.0000000020.0000000001","gameVersion":"1.20.1","gameVersionReleaseDate":"2023-06-12T14:26:38.477Z","gameVersionName":"1.20.1","gameVersionTypeId":75125},{"gameVersionPadded":"0","gameVersion":"","gameVersionReleaseDate":"2022-10-01T00:00:00Z","gameVersionName":"Forge","gameVersionTypeId":68441}],"downloadUrl":"https://edge.forgecdn.net/files/5613/231/mcjtylib-1.20-8.0.6.jar","fileDate":"2024-08-10T04:42:53.127Z","exposeAsAlternative":null,"modId":233105,"modules":[{"name":"META-INF","fingerprint":2905271689},{"name":"mcjty","fingerprint":3035213789},{"name":"assets","fingerprint":3529305187},{"name":"pack.mcmeta","fingerprint":3310931799}],"dependencies":[{"relationType":2,"modId":245211}],"fileFingerprint":3953430503,"fileStatus":4,"releaseType":1,"hashes":[{"value":"300afa123362f6f10c3791cc28d7086417379dad","algo":1},{"value":"318269b38df6cca8bfe7fec0a16cc644","algo":2}],"parentProjectFileId":null,"alternateFileId":0,"id":5613231,"fileLength":675157,"downloadCount":1632029,"serverPackFileId":null,"serverPack":false,"available":false},{"gameId":432,"fileName":"mcjtylib-1.21-9.0.3.jar","gameVersions":["1.21.1"],"displayName":"McJtyLib - 1.21-9.0.3","sortableGameVersions":[{"gameVersionPadded":"0000000001.0000000021.0000000001","gameVersion":"1.21.1","gameVersionReleaseDate":"2024-08-08T15:17:53.787Z","gameVersionName":"1.21.1","gameVersionTypeId":77784}],"downloadUrl":"https://edge.forgecdn.net/files/5830/986/mcjtylib-1.21-9.0.3.jar","fileDate":"2024-10-21T15:19:57.557Z","exposeAsAlternative":null,"modId":233105,"modules":[{"name":"META-INF","fingerprint":2142130036},{"name":"mcjty","fingerprint":4199245704},{"name":"assets","fingerprint":3529305187}],"dependencies":[{"relationType":2,"modId":245211}],"fileFingerprint":4086056177,"fileStatus":4,"releaseType":2,"hashes":[{"value":"5396d840761677e6aa522c67a81232d807800000","algo":1},{"value":"af6752986390e9f72d669f642a3b3f40","algo":2}],"parentProjectFileId":null,"alternateFileId":0,"id":5830986,"fileLength":687269,"downloadCount":0,"serverPackFileId":null,"serverPack":false,"available":false},{"gameId":432,"fileName":"mcjtylib-1.21-9.0.5.jar","gameVersions":["NeoForge","1.21.1"],"displayName":"McJtyLib - 1.21-9.0.5","sortableGameVersions":[{"gameVersionPadded":"0","gameVersion":"","gameVersionReleaseDate":"2023-07-25T00:00:00Z","gameVersionName":"NeoForge","gameVersionTypeId":68441},{"gameVersionPadded":"0000000001.0000000021.0000000001","gameVersion":"1.21.1","gameVersionReleaseDate":"2024-08-08T15:17:53.787Z","gameVersionName":"1.21.1","gameVersionTypeId":77784}],"downloadUrl":"https://edge.forgecdn.net/files/5961/438/mcjtylib-1.21-9.0.5.jar","fileDate":"2024-12-04T05:50:51.633Z","exposeAsAlternative":null,"modId":233105,"modules":[{"name":"META-INF","fingerprint":2180357154},{"name":"mcjty","fingerprint":4235124189},{"name":"assets","fingerprint":3529305187}],"dependencies":[{"relationType":2,"modId":245211}],"fileFingerprint":1685815595,"fileStatus":4,"releaseType":2,"hashes":[{"value":"d63cfc6f70a1256af3827d653e21b3c5423cbb44","algo":1},{"value":"e49bf4ade804d463ffbdac191be730a8","algo":2}],"parentProjectFileId":null,"alternateFileId":0,"id":5961438,"fileLength":697896,"downloadCount":0,"serverPackFileId":null,"serverPack":false,"available":false}],"dateModified":"2024-12-04T05:56:45.243Z","gamePopularityRank":243,"thumbsUpCount":0,"name":"McJtyLib","mainFileId":5613231,"primaryCategoryId":421,"downloadCount":140563954,"status":4,"authors":[{"name":"McJty","id":12351286,"url":"https://www.curseforge.com/members/mcjty"}],"available":false,"featured":false}