{"allowModDistribution":true,"screenshots":[],"classId":6,"latestFilesIndexes":[{"filename":"rftoolscontrol-1.20-7.0.3.jar","releaseType":1,"gameVersion":"1.20.1","gameVersionTypeId":75125,"modLoader":1,"fileId":5846562},{"filename":"rftoolscontrol-1.19-6.1.5.jar","releaseType":1,"gameVersion":"1.19.3","gameVersionTypeId":73407,"modLoader":1,"fileId":5294706},{"filename":"rftoolscontrol-1.19-6.1.5.jar","releaseType":1,"gameVersion":"1.19.4","gameVersionTypeId":73407,"modLoader":1,"fileId":5294706},{"filename":"rftoolscontrol-1.19-6.1.5.jar","releaseType":1,"gameVersion":"1.19.2","gameVersionTypeId":73407,"modLoader":1,"fileId":5294706},{"filename":"rftoolscontrol-1.20-7.0.0.jar","releaseType":2,"gameVersion":"1.20.1","gameVersionTypeId":75125,"modLoader":1,"fileId":4598239},{"filename":"rftoolscontrol-1.18-5.0.10.jar","releaseType":1,"gameVersion":"1.18.2","gameVersionTypeId":73250,"modLoader":1,"fileId":4379832},{"filename":"rftoolscontrol-1.19-6.0.0.jar","releaseType":2,"gameVersion":"1.19.1","gameVersionTypeId":73407,"modLoader":1,"fileId":3900113},{"filename":"rftoolscontrol-1.19-6.0.0.jar","releaseType":2,"gameVersion":"1.19","gameVersionTypeId":73407,"modLoader":1,"fileId":3900113},{"filename":"rftoolscontrol-1.16-4.0.18.jar","releaseType":1,"gameVersion":"1.16.5","gameVersionTypeId":70886,"modLoader":1,"fileId":3813661},{"filename":"rftoolscontrol-1.18-5.0.4.jar","releaseType":2,"gameVersion":"1.18.2","gameVersionTypeId":73250,"modLoader":1,"fileId":3753621},{"filename":"rftoolscontrol-1.18-5.0.1.jar","releaseType":2,"gameVersion":"1.18.1","gameVersionTypeId":73250,"modLoader":1,"fileId":3603060},{"filename":"rftoolscontrol-1.16-4.0.7.jar","releaseType":1,"gameVersion":"1.16.3","gameVersionTypeId":70886,"modLoader":1,"fileId":3194359},{"filename":"rftoolscontrol-1.16-4.0.7.jar","releaseType":1,"gameVersion":"1.16.4","gameVersionTypeId":70886,"modLoader":1,"fileId":3194359},{"filename":"rftoolscontrol-1.15-3.0.9.jar","releaseType":1,"gameVersion":"1.15.2","gameVersionTypeId":68722,"modLoader":1,"fileId":3096836},{"filename":"rftoolscontrol-1.16-4.0.5.jar","releaseType":1,"gameVersion":"1.16.2","gameVersionTypeId":70886,"modLoader":1,"fileId":3057537},{"filename":"rftoolscontrol-1.16-4.0.4-beta.jar","releaseType":2,"gameVersion":"1.16.2","gameVersionTypeId":70886,"modLoader":1,"fileId":3049320},{"filename":"rftoolscontrol-1.15-3.0.4-beta.jar","releaseType":2,"gameVersion":"1.15.2","gameVersionTypeId":68722,"modLoader":1,"fileId":3014092},{"filename":"rftoolsctrl-1.12-2.0.2.jar","releaseType":1,"gameVersion":"1.12.2","gameVersionTypeId":628,"modLoader":null,"fileId":2705813},{"filename":"rftoolsctrl-1.12-1.9.0-alpha.jar","releaseType":3,"gameVersion":"1.12.2","gameVersionTypeId":628,"modLoader":null,"fileId":2567296},{"filename":"rftoolsctrl-1.12-1.7.0.jar","releaseType":1,"gameVersion":"1.12.1","gameVersionTypeId":628,"modLoader":null,"fileId":2503244},{"filename":"rftoolsctrl-1.1x-1.7.0.jar","releaseType":1,"gameVersion":"1.10.2","gameVersionTypeId":572,"modLoader":null,"fileId":2503243},{"filename":"rftoolsctrl-1.1x-1.7.0.jar","releaseType":1,"gameVersion":"1.11.2","gameVersionTypeId":599,"modLoader":null,"fileId":2503243},{"filename":"rftoolsctrl-1.12-1.6.8.jar","releaseType":1,"gameVersion":"1.12","gameVersionTypeId":628,"modLoader":null,"fileId":2451161},{"filename":"rftoolsctrl-1.12-1.6.8beta1.jar","releaseType":2,"gameVersion":"1.12","gameVersionTypeId":628,"modLoader":null,"fileId":2443321},{"filename":"rftoolsctrl-1.1x-1.6.6.jar","releaseType":1,"gameVersion":"1.11","gameVersionTypeId":599,"modLoader":null,"fileId":2379523},{"filename":"rftoolsctrl-1.11-1.5.2beta1.jar","releaseType":2,"gameVersion":"1.10.2","gameVersionTypeId":572,"modLoader":null,"fileId":2351207},{"filename":"rftoolsctrl-1.11-1.5.2beta1.jar","releaseType":2,"gameVersion":"1.11","gameVersionTypeId":599,"modLoader":null,"fileId":2351207},{"filename":"rftoolsctrl-1.11-1.5.2alpha2.jar","releaseType":3,"gameVersion":"1.10.2","gameVersionTypeId":572,"modLoader":null,"fileId":2350550},{"filename":"rftoolsctrl-1.11-1.5.2alpha2.jar","releaseType":3,"gameVersion":"1.11","gameVersionTypeId":599,"modLoader":null,"fileId":2350550}],"dateCreated":"2016-09-06T18:21:11.823Z","logo":{"description":"","id":50211,"title":"636087648718872179.png","modId":250763,"url":"https://media.forgecdn.net/avatars/50/211/636087648718872179.png","thumbnailUrl":"https://media.forgecdn.net/avatars/thumbnails/50/211/256/256/636087648718872179.png"},"links":{"sourceUrl":null,"issuesUrl":"https://github.com/McJty/RFToolsControl/issues","websiteUrl":"https://www.curseforge.com/minecraft/mc-mods/rftools-control","wikiUrl":""},"dateReleased":"2024-10-26T05:10:04.6Z","id":250763,"categories":[{"gameId":432,"classId":6,"name":"Technology","dateModified":"2014-05-08T17:37:54.597Z","parentCategoryId":6,"id":412,"iconUrl":"https://media.forgecdn.net/avatars/6/27/635351494745973439.png","slug":"technology","url":"https://www.curseforge.com/minecraft/mc-mods/technology","displayIndex":0,"class":false},{"gameId":432,"classId":6,"name":"Energy, Fluid, and Item Transport","dateModified":"2014-05-08T17:39:07.873Z","parentCategoryId":412,"id":415,"iconUrl":"https://media.forgecdn.net/avatars/6/30/635351495478719291.png","slug":"technology-item-fluid-energy-transport","url":"https://www.curseforge.com/minecraft/mc-mods/technology/technology-item-fluid-energy-transport","displayIndex":0,"class":false}],"slug":"rftools-control","gameId":432,"summary":"Automation and logic computer addon for RFTools","latestFiles":[{"gameId":432,"fileName":"rftoolsctrl-1.12-1.6.8beta1.jar","gameVersions":["1.12"],"displayName":"rftoolsctrl-1.12-1.6.8beta1.jar","sortableGameVersions":[{"gameVersionPadded":"0000000001.0000000012","gameVersion":"1.12","gameVersionReleaseDate":"2017-06-07T05:00:00Z","gameVersionName":"1.12","gameVersionTypeId":628}],"downloadUrl":"https://edge.forgecdn.net/files/2443/321/rftoolsctrl-1.12-1.6.8beta1.jar","fileDate":"2017-06-29T15:36:33.537Z","exposeAsAlternative":null,"modId":250763,"modules":[{"name":"META-INF","fingerprint":2464251221},{"name":"mcjty","fingerprint":2953839545},{"name":"mcmod.info","fingerprint":1781302275},{"name":"pack.mcmeta","fingerprint":2096217380},{"name":"assets","fingerprint":1039529536}],"dependencies":[{"relationType":3,"modId":224641},{"relationType":3,"modId":233105},{"relationType":2,"modId":245211}],"fileFingerprint":1534303665,"fileStatus":4,"releaseType":2,"hashes":[{"value":"7e5d720cfb30547099e348720fc2e3caaf0964b0","algo":1},{"value":"66d68524917249f49d2e8f85ff74c859","algo":2}],"parentProjectFileId":null,"alternateFileId":0,"id":2443321,"fileLength":581597,"downloadCount":24530,"serverPackFileId":null,"serverPack":false,"available":false},{"gameId":432,"fileName":"rftoolsctrl-1.12-1.9.0-alpha.jar","gameVersions":["1.12.2"],"displayName":"RFToolsControl - 1.12-1.9.0-alpha","sortableGameVersions":[{"gameVersionPadded":"0000000001.0000000012.0000000002","gameVersion":"1.12.2","gameVersionReleaseDate":"2017-09-18T05:00:00Z","gameVersionName":"1.12.2","gameVersionTypeId":628}],"downloadUrl":"https://edge.forgecdn.net/files/2567/296/rftoolsctrl-1.12-1.9.0-alpha.jar","fileDate":"2018-05-29T18:08:12.393Z","exposeAsAlternative":null,"modId":250763,"modules":[{"name":"META-INF","fingerprint":3298717741},{"name":"mcjty","fingerprint":394109754},{"name":"mcmod.info","fingerprint":1662206833},{"name":"pack.mcmeta","fingerprint":1984565353},{"name":"assets","fingerprint":1352878465}],"dependencies":[{"relationType":2,"modId":245211},{"relationType":3,"modId":233105},{"relationType":2,"modId":270789},{"relationType":3,"modId":224641}],"fileFingerprint":2821236720,"fileStatus":4,"releaseType":3,"hashes":[{"value":"3348eabf2cb09d44a9b74c9c100a5b7249997dd9","algo":1},{"value":"446e7762d22bb1acd15665692e87e859","algo":2}],"parentProjectFileId":null,"alternateFileId":0,"id":2567296,"fileLength":590743,"downloadCount":13838,"serverPackFileId":null,"serverPack":false,"available":false},{"gameId":432,"fileName":"rftoolsctrl-1.12-2.0.2.jar","gameVersions":["1.12.2"],"displayName":"RFToolsControl - 1.12-2.0.2","sortableGameVersions":[{"gameVersionPadded":"0000000001.0000000012.0000000002","gameVersion":"1.12.2","gameVersionReleaseDate":"2017-09-18T05:00:00Z","gameVersionName":"1.12.2","gameVersionTypeId":628}],"downloadUrl":"https://edge.forgecdn.net/files/2705/813/rftoolsctrl-1.12-2.0.2.jar","fileDate":"2019-05-01T04:37:55.937Z","exposeAsAlternative":null,"modId":250763,"modules":[{"name":"META-INF","fingerprint":1357189213},{"name":"mcjty","fingerprint":4154545413},{"name":"mcmod.info","fingerprint":2695639641},{"name":"pack.mcmeta","fingerprint":1984565353},{"name":"assets","fingerprint":1484899670}],"dependencies":[{"relationType":2,"modId":245211},{"relationType":3,"modId":233105},{"relationType":2,"modId":270789},{"relationType":3,"modId":224641}],"fileFingerprint":1940565279,"fileStatus":4,"releaseType":1,"hashes":[{"value":"1f69d5554351998c9df8a8bbc6ac139c4f6a10da","algo":1},{"value":"640e2b3241acde04684bd904829959ad","algo":2}],"parentProjectFileId":null,"alternateFileId":0,"id":2705813,"fileLength":600728,"downloadCount":18530823,"serverPackFileId":null,"serverPack":false,"available":false},{"gameId":432,"fileName":"rftoolscontrol-1.20-7.0.0.jar","gameVersions":["1.20.1","Forge"],"displayName":"RFToolsControl - 1.20-7.0.0","sortableGameVersions":[{"gameVersionPadded":"0000000001.0000000020.0000000001","gameVersion":"1.20.1","gameVersionReleaseDate":"2023-06-12T14:26:38.477Z","gameVersionName":"1.20.1","gameVersionTypeId":75125},{"gameVersionPadded":"0","gameVersion":"","gameVersionReleaseDate":"2022-10-01T00:00:00Z","gameVersionName":"Forge","gameVersionTypeId":68441}],"downloadUrl":"https://edge.forgecdn.net/files/4598/239/rftoolscontrol-1.20-7.0.0.jar","fileDate":"2023-06-20T06:16:04.190Z","exposeAsAlternative":null,"modId":250763,"modules":[{"name":"META-INF","fingerprint":711474255},{"name":"mcjty","fingerprint":533584757},{"name":"assets","fingerprint":3524129932},{"name":"data","fingerprint":3823336742},{"name":"pack.mcmeta","fingerprint":2473535451}],"dependencies":[{"relationType":3,"modId":233105},{"relationType":3,"modId":326041},{"relationType":2,"modId":245211}],"fileFingerprint":1475772743,"fileStatus":4,"releaseType":2,"hashes":[{"value":"e73483a75afebf8ededebd6b26e9cf2e960bc8c5","algo":1},{"value":"42332aa2d888fbb7ee723ed91c364388","algo":2}],"parentProjectFileId":null,"alternateFileId":0,"id":4598239,"fileLength":589639,"downloadCount":625358,"serverPackFileId":null,"serverPack":false,"available":false},{"gameId":432,"fileName":"rftoolscontrol-1.20-7.0.3.jar","gameVersions":["1.20.1","Forge"],"displayName":"RFToolsControl - 1.20-7.0.3","sortableGameVersions":[{"gameVersionPadded":"0000000001.0000000020.0000000001","gameVersion":"1.20.1","gameVersionReleaseDate":"2023-06-12T14:26:38.477Z","gameVersionName":"1.20.1","gameVersionTypeId":75125},{"gameVersionPadded":"0","gameVersion":"","gameVersionReleaseDate":"2022-10-01T00:00:00Z","gameVersionName":"Forge","gameVersionTypeId":68441}],"downloadUrl":"https://edge.forgecdn.net/files/5846/562/rftoolscontrol-1.20-7.0.3.jar","fileDate":"2024-10-26T05:10:04.600Z","exposeAsAlternative":null,"modId":250763,"modules":[{"name":"META-INF","fingerprint":3442379615},{"name":"mcjty","fingerprint":780580218},{"name":"assets","fingerprint":1189070749},{"name":"data","fingerprint":2110554191},{"name":"pack.mcmeta","fingerprint":2473535451}],"dependencies":[{"relationType":2,"modId":245211},{"relationType":3,"modId":326041},{"relationType":3,"modId":233105}],"fileFingerprint":1970022193,"fileStatus":4,"releaseType":1,"hashes":[{"value":"69c4cc728950225154c03af8814347a90d660ab3","algo":1},{"value":"0fcd624899060cd2d8e9d7a5f3f53860","algo":2}],"parentProjectFileId":null,"alternateFileId":0,"id":5846562,"fileLength":594137,"downloadCount":627,"serverPackFileId":null,"serverPack":false,"available":false}],"dateModified":"2024-10-26T05:15:34.063Z","gamePopularityRank":847,"thumbsUpCount":0,"name":"RFTools Control","mainFileId":5846562,"primaryCategoryId":412,"downloadCount":69324967,"status":4,"authors":[{"name":"McJty","id":12351286,"url":"https://www.curseforge.com/members/mcjty"}],"available":false,"featured":false}