{"gameId":432,"fileName":"cloth-config-11.1.136-forge.jar","gameVersions":["NeoForge","1.20.1","Forge","1.20"],"displayName":"[Forge 1.20(.1)] v11.1.136","sortableGameVersions":[{"gameVersionPadded":"0","gameVersion":"","gameVersionReleaseDate":"2023-07-25T00:00:00Z","gameVersionName":"NeoForge","gameVersionTypeId":68441},{"gameVersionPadded":"0000000001.0000000020.0000000001","gameVersion":"1.20.1","gameVersionReleaseDate":"2023-06-12T14:26:38.477Z","gameVersionName":"1.20.1","gameVersionTypeId":75125},{"gameVersionPadded":"0","gameVersion":"","gameVersionReleaseDate":"2022-10-01T00:00:00Z","gameVersionName":"Forge","gameVersionTypeId":68441},{"gameVersionPadded":"0000000001.0000000020","gameVersion":"1.20","gameVersionReleaseDate":"2023-06-07T00:00:00Z","gameVersionName":"1.20","gameVersionTypeId":75125}],"downloadUrl":"https://edge.forgecdn.net/files/5729/105/cloth-config-11.1.136-forge.jar","fileDate":"2024-09-16T17:13:48.940Z","exposeAsAlternative":null,"modId":348521,"modules":[{"name":"META-INF","fingerprint":1331850120},{"name":"LICENSE.md","fingerprint":4008471873},{"name":"assets","fingerprint":3854573463},{"name":"pack.mcmeta","fingerprint":524945892},{"name":"icon.png","fingerprint":2356087988},{"name":"me","fingerprint":4258044106},{"name":"architectury_inject_clothconfig_common_0b9ec81698d34ba0a2990a6d342e97cf_da5b50464723222034f823fb516e12f8be65f5546163a096669cd65445ae7540clothconfig111136devjar","fingerprint":3445087113}],"dependencies":[],"fileFingerprint":635589968,"fileStatus":4,"releaseType":1,"hashes":[{"value":"c65d07748acc57ceb45d53b3964368b84f34d54f","algo":1},{"value":"ca5de5acbcb4a30c010aa6953bd7ef53","algo":2}],"parentProjectFileId":null,"alternateFileId":0,"id":5729105,"fileLength":1181413,"downloadCount":15213,"serverPackFileId":null,"serverPack":false,"available":false}