{"gameId":432,"fileName":"createaddition-1.20.1-1.2.4e.jar","gameVersions":["Client","1.20.1","Forge","Server"],"displayName":"createaddition-forge-1.20.1-1.2.4e","sortableGameVersions":[{"gameVersionPadded":"0","gameVersion":"","gameVersionReleaseDate":"2022-12-08T00:00:00Z","gameVersionName":"Client","gameVersionTypeId":75208},{"gameVersionPadded":"0000000001.0000000020.0000000001","gameVersion":"1.20.1","gameVersionReleaseDate":"2023-06-12T14:26:38.477Z","gameVersionName":"1.20.1","gameVersionTypeId":75125},{"gameVersionPadded":"0","gameVersion":"","gameVersionReleaseDate":"2022-10-01T00:00:00Z","gameVersionName":"Forge","gameVersionTypeId":68441},{"gameVersionPadded":"0","gameVersion":"","gameVersionReleaseDate":"2022-12-08T00:00:00Z","gameVersionName":"Server","gameVersionTypeId":75208}],"downloadUrl":"https://edge.forgecdn.net/files/5658/602/createaddition-1.20.1-1.2.4e.jar","fileDate":"2024-08-24T10:29:04.587Z","exposeAsAlternative":null,"modId":439890,"modules":[{"name":"META-INF","fingerprint":3495238616},{"name":"assets","fingerprint":4180208942},{"name":"com","fingerprint":1799252492},{"name":"createaddition.mixins.json","fingerprint":2693430505},{"name":"createaddition.refmap.json","fingerprint":1493072104},{"name":"data","fingerprint":1357379440},{"name":"pack.mcmeta","fingerprint":1438559181}],"dependencies":[{"relationType":2,"modId":238222},{"relationType":3,"modId":328085}],"fileFingerprint":1415544755,"fileStatus":4,"releaseType":1,"hashes":[{"value":"41f22b70ceb9f61db0306871f2ae9998b25ed4fd","algo":1},{"value":"49574e04bf858f06464066d51df19bca","algo":2}],"parentProjectFileId":null,"alternateFileId":0,"id":5658602,"fileLength":1515917,"downloadCount":386402,"serverPackFileId":null,"serverPack":false,"available":false}