{"gameId":432,"fileName":"BasicNetherOres-forge-1.20.1-9.1.1.jar","gameVersions":["1.20.1","Forge"],"displayName":"Basic Nether Ores-1.20.1-9.1.1 - Forge","sortableGameVersions":[{"gameVersionPadded":"0000000001.0000000020.0000000001","gameVersion":"1.20.1","gameVersionReleaseDate":"2023-06-12T14:26:38.477Z","gameVersionName":"1.20.1","gameVersionTypeId":75125},{"gameVersionPadded":"0","gameVersion":"","gameVersionReleaseDate":"2022-10-01T00:00:00Z","gameVersionName":"Forge","gameVersionTypeId":68441}],"downloadUrl":"https://edge.forgecdn.net/files/4723/590/BasicNetherOres-forge-1.20.1-9.1.1.jar","fileDate":"2023-08-26T20:36:57.400Z","exposeAsAlternative":null,"modId":289647,"modules":[{"name":"META-INF","fingerprint":897117241},{"name":".cache","fingerprint":1507378683},{"name":"LICENSE_BasicNetherOres","fingerprint":1825142702},{"name":"assets","fingerprint":3322296171},{"name":"bno-logo.png","fingerprint":1659011827},{"name":"bno.forge.mixins.json","fingerprint":185201532},{"name":"bno.mixins.json","fingerprint":185201532},{"name":"data","fingerprint":2288079617},{"name":"net","fingerprint":450702995},{"name":"opt_in","fingerprint":178503832},{"name":"pack.mcmeta","fingerprint":2074644460}],"dependencies":[],"fileFingerprint":290473527,"fileStatus":4,"releaseType":1,"hashes":[{"value":"34361a275967f29a3c6e3737484443304426734c","algo":1},{"value":"9f4a575782a99c4cfa6b3cce7ddf718e","algo":2}],"parentProjectFileId":null,"alternateFileId":4723593,"id":4723590,"fileLength":599056,"downloadCount":411746,"serverPackFileId":null,"serverPack":false,"available":false}